ohlc_data/__init__.py
ohlc_data/authenticate.py
ohlc_data/main.py
ohlc_data/ohlc.py
ohlc_data/scripts.py
ohlc_data/source_select.py
ohlc_data/ticker_select.py
ohlc_data/utils.py
ohlc_data-1.1.3.dist-info/LICENSE
ohlc_data-1.1.3.dist-info/METADATA
ohlc_data-1.1.3.dist-info/WHEEL
ohlc_data-1.1.3.dist-info/entry_points.txt
ohlc_data-1.1.3.dist-info/RECORD
