Metadata-Version: 2.3
Name: ohlc-data
Version: 1.1.3
Summary: 
Author: Alejandro_Wong
Author-email: alejandroawong@gmail.com
Requires-Python: >=3.11,<4.0.0
Classifier: Programming Language :: Python :: 3
Classifier: Programming Language :: Python :: 3.11
Classifier: Programming Language :: Python :: 3.12
Classifier: Programming Language :: Python :: 3.13
Requires-Dist: alpaca-py (>=0.42.0,<0.43.0)
Requires-Dist: numpy (>=2.2.0,<3.0.0)
Requires-Dist: pandas (>=2.3.1,<3.0.0)
Requires-Dist: python-dotenv (>=1.1.1,<2.0.0)
Requires-Dist: simple-term-menu (>=1.6.6)
Requires-Dist: yfinance (>=0.2.65,<0.3.0)
